bosdyn/__init__.py
bosdyn/scout/__init__.py
bosdyn/scout/client.py
bosdyn/scout/exceptions.py
bosdyn/scout/utils.py
bosdyn_scout-5.0.1.1.dist-info/METADATA
bosdyn_scout-5.0.1.1.dist-info/WHEEL
bosdyn_scout-5.0.1.1.dist-info/top_level.txt
bosdyn_scout-5.0.1.1.dist-info/RECORD
