Metadata-Version: 2.1
Name: bosdyn-scout
Version: 5.0.1.1
Summary: Boston Dynamics API Scout Client
Home-page: https://dev.bostondynamics.com/docs/scout/
Author: Boston Dynamics
Author-email: support@bostondynamics.com
Project-URL: Documentation, https://dev.bostondynamics.com/docs/scout/
Project-URL: Source, https://github.com/boston-dynamics/spot-sdk/
Classifier: Programming Language :: Python :: 3.6
Classifier: Programming Language :: Python :: 3.7
Classifier: Programming Language :: Python :: 3.8
Classifier: Programming Language :: Python :: 3.9
Classifier: Programming Language :: Python :: 3.10
Classifier: License :: Other/Proprietary License
Classifier: Operating System :: OS Independent
Requires-Python: >=3.6
Requires-Dist: requests
Requires-Dist: Deprecated (~=1.2.10)
Requires-Dist: bosdyn-orbit (==5.0.1.1)
